agzline/TalkService.py
agzline/__init__.py
agzline/constants.py
agzline/ttypes.py
agzline-0.1.2.dist-info/METADATA
agzline-0.1.2.dist-info/WHEEL
agzline-0.1.2.dist-info/top_level.txt
agzline-0.1.2.dist-info/RECORD
